MANIFEST.in
README.md
setup.py
tests/__init__.py
tests/test_Phenotype.py
tests/test_pfam.py
traitar/PhenotypeCollection.py
traitar/__init__.py
traitar/__main__.py
traitar/_version.py
traitar/domtblout2gene_generic.py
traitar/evaluation.py
traitar/get_external_data.py
traitar/heatmap.py
traitar/hmm2gff.py
traitar/hmmer2filtered_best.py
traitar/merge_preds.py
traitar/modify.py
traitar/predict.py
traitar/traitar_cls.py
traitar/utils.py
traitar/Commands/__init__.py
traitar/Commands/annotate.py
traitar/Commands/evaluate.py
traitar/Commands/new.py
traitar/Commands/pfam.py
traitar/Commands/phenotype.py
traitar/Commands/remove.py
traitar/Commands/show.py
traitar/data/colors.txt
traitar/data/models/phypat+PGL.tar.gz
traitar/data/models/phypat.tar.gz
traitar/data/sample_data/1457190.3.RefSeq.faa
traitar/data/sample_data/1457190.3.RefSeq.gff
traitar/data/sample_data/525367.9.RefSeq.faa
traitar/data/sample_data/525367.9.RefSeq.gff
traitar/data/sample_data/samples.txt
traitar/data/sample_data/samples_gene_gff.txt
traitar/data/sample_data/traitar_out/annotation/pfam/Listeria_grayi_DSM_20601_domtblout.dat
traitar/data/sample_data/traitar_out/annotation/pfam/Listeria_grayi_DSM_20601_filtered_best.dat
traitar/data/sample_data/traitar_out/annotation/pfam/Listeria_ivanovii_WSLC3009_domtblout.dat
traitar/data/sample_data/traitar_out/annotation/pfam/Listeria_ivanovii_WSLC3009_filtered_best.dat
traitar/data/sample_data/traitar_out/annotation/pfam/joblog_filter_and_aggregate.txt
traitar/data/sample_data/traitar_out/annotation/pfam/joblog_filter_and_aggregate_recompute.txt
traitar/data/sample_data/traitar_out/annotation/pfam/joblog_generate_annotation_matrix.txt
traitar/data/sample_data/traitar_out/annotation/pfam/joblog_hmmer.txt
traitar/data/sample_data/traitar_out/annotation/pfam/joblog_hmmer_recompute.txt
traitar/data/sample_data/traitar_out/annotation/pfam/summary.dat
traitar/data/sample_data/traitar_out/phenotype_prediction/feature_track_commands.txt
traitar3.egg-info/PKG-INFO
traitar3.egg-info/SOURCES.txt
traitar3.egg-info/dependency_links.txt
traitar3.egg-info/entry_points.txt
traitar3.egg-info/not-zip-safe
traitar3.egg-info/requires.txt
traitar3.egg-info/top_level.txt